rightchain/__init__.py
rightchain/__main__.py
rightchain/application/__init__.py
rightchain/application/my_controller.py
rightchain/domain/__init__.py
rightchain/domain/models/__init__.py
rightchain/domain/models/file.py
rightchain/domain/models/index_record.py
rightchain/domain/models/repo_status.py
rightchain/domain/services/__init__.py
rightchain/domain/services/indexing.py
rightchain/infra/__init__.py
rightchain/infra/client.py
rightchain/infra/copyright_store_service.py
rightchain/infra/file_lister.py
rightchain/infra/git_service.py
rightchain-0.1.5.data/scripts/rccc
rightchain-0.1.5.data/scripts/rccc.ps1
rightchain-0.1.5.dist-info/METADATA
rightchain-0.1.5.dist-info/WHEEL
rightchain-0.1.5.dist-info/top_level.txt
rightchain-0.1.5.dist-info/RECORD
